ShynaTwelveAM/__init__.py
ShynaTwelveAM/shynatwelveam.py
ShynaTwelveAM-0.0.6.dist-info/LICENSE
ShynaTwelveAM-0.0.6.dist-info/METADATA
ShynaTwelveAM-0.0.6.dist-info/WHEEL
ShynaTwelveAM-0.0.6.dist-info/top_level.txt
ShynaTwelveAM-0.0.6.dist-info/RECORD
