Metadata-Version: 2.1
Name: ShynaTwelveAM
Version: 0.0.6
Summary: This package processes Shyna's 12 AM tasks
Author: Shivam Sharma
Author-email: shivamsharma1913@gmail.com
License-File: LICENSE
Requires-Dist: setuptools
Requires-Dist: wheel
Requires-Dist: ShynaDatabase
Requires-Dist: ShynaWeather
Requires-Dist: Shynatime
Requires-Dist: wget
